CablyAiAPI/__init__.py
CablyAiAPI/api.py
cablyaiapi-0.0.1.dist-info/METADATA
cablyaiapi-0.0.1.dist-info/WHEEL
cablyaiapi-0.0.1.dist-info/top_level.txt
cablyaiapi-0.0.1.dist-info/RECORD
